mlfsm/__init__.py
mlfsm/coords.py
mlfsm/cos.py
mlfsm/geom.py
mlfsm/interp.py
mlfsm/opt.py
mlfsm/py.typed
mlfsm/pytest.ini
mlfsm/utils.py
mlfsm-1.0.0.dist-info/METADATA
mlfsm-1.0.0.dist-info/WHEEL
mlfsm-1.0.0.dist-info/licenses/LICENSE
mlfsm-1.0.0.dist-info/RECORD
