Metadata-Version: 2.4
Name: mlfsm
Version: 1.0.0
Summary: python implementation of the Freezing String Method
Project-URL: Homepage, https://github.com/jonmarks12/mlfsm
Project-URL: Repository, https://github.com/jonmarks12/mlfsm
Project-URL: Issues, https://github.com/jonmarks12/mlfsm/issues
Author-email: Jonah Marks and Joe Gomes <jonahmarks22@gmail.com>
Maintainer: Jonah Marks
License: MIT License
License-File: LICENSE
Requires-Python: >=3.11
Requires-Dist: ase>=3.22
Requires-Dist: geometric>=1.0.0
Requires-Dist: networkx>=3.0
Requires-Dist: numpy>=1.26
Requires-Dist: scipy>=1.13
